visio_mcp_server/__init__.py
visio_mcp_server/visio_server.py
office_visio_mcp_server-1.0.1.dist-info/METADATA
office_visio_mcp_server-1.0.1.dist-info/WHEEL
office_visio_mcp_server-1.0.1.dist-info/entry_points.txt
office_visio_mcp_server-1.0.1.dist-info/licenses/LICENSE
office_visio_mcp_server-1.0.1.dist-info/RECORD
