Metadata-Version: 2.4
Name: office-visio-mcp-server
Version: 1.0.1
Summary: MCP server for manipulating Microsoft Visio documents
Project-URL: Homepage, https://github.com/GongRzhe/Office-Visio-MCP-Server
Project-URL: Bug Tracker, https://github.com/GongRzhe/Office-Visio-MCP-Server/issues
Author-email: GongRzhe <gongrzhe@gmail.com>
License: MIT License
License-File: LICENSE
Classifier: License :: OSI Approved :: MIT License
Classifier: Operating System :: Microsoft :: Windows
Classifier: Programming Language :: Python :: 3
Requires-Python: >=3.8
Requires-Dist: mcp[cli]>=1.2.0
Requires-Dist: pywin32>=305
